tlmulticlient/__init__.py
tlmulticlient-0.0.4.dist-info/LICENSE
tlmulticlient-0.0.4.dist-info/METADATA
tlmulticlient-0.0.4.dist-info/WHEEL
tlmulticlient-0.0.4.dist-info/top_level.txt
tlmulticlient-0.0.4.dist-info/RECORD
