Metadata-Version: 2.1
Name: tlmulticlient
Version: 0.0.4
Summary: Multi Sessions addon for Telethon
Home-page: UNKNOWN
Author: Nitan Alexandru Marcel
Author-email: nitan.marcel@protonmail.com
License: MIT
Project-URL: Donations, https://paypal.me/marcelalexandrunitan?locale.x=en_US
Project-URL: Source, https://github.com/nitanmarcel/tlmulticlient
Keywords: telethon telegram telegram-client
Platform: any
Classifier: Intended Audience :: Developers
Classifier: Operating System :: OS Independent
Classifier: Programming Language :: Python :: 3.6
Classifier: Programming Language :: Python :: 3.7
Classifier: Programming Language :: Python :: 3.8
Classifier: Programming Language :: Python :: 3.9
Classifier: Topic :: Software Development :: Libraries :: Python Modules
Requires-Dist: telethon
